{
"companyName": "DefaultCompany",
"productName": "HummingBird",
"productVersion": "0.1",
"dataUrl": "Assigmnet4B.data.unityweb",
"wasmCodeUrl": "Assigmnet4B.wasm.code.unityweb",
"wasmFrameworkUrl": "Assigmnet4B.wasm.framework.unityweb",
"graphicsAPI": ["WebGL 2.0"],
"webglContextAttributes": {"preserveDrawingBuffer": false},
"splashScreenStyle": "Dark",
"backgroundColor": "#2F4343",
"cacheControl": {"default": "must-revalidate"},
"developmentBuild": false,
"multithreading": false,
"unityVersion": "2019.3.12f1"
}